asycnapixui/__init__.py
asycnapixui/api.py
asycnapixui/log.py
asycnapixui/models.py
asycnapixui/utils.py
asycnapixui-0.0.3.dist-info/METADATA
asycnapixui-0.0.3.dist-info/WHEEL
asycnapixui-0.0.3.dist-info/licenses/LICENSE
asycnapixui-0.0.3.dist-info/RECORD
