Metadata-Version: 2.4
Name: asycnapixui
Version: 0.0.3
Summary: Asynchronous api module for 3x-ui
Project-URL: Homepage, https://github.com/qrustik/asyncapixui
Project-URL: Issues, https://github.com/qrustik/asyncapixui/issues
Author-email: qrustik <rusteamplay@gmail.com>
License-File: LICENSE
Classifier: License :: OSI Approved :: MIT License
Classifier: Operating System :: OS Independent
Classifier: Programming Language :: Python :: 3
Requires-Python: >=3.11
Requires-Dist: aiohttp
Requires-Dist: pydantic
